{
  "Fast Blade": "재빠른 검격",
  "Riot Blade": "폭도의 검격",
  "Royal Authority": "제왕의 권위",
  "Atonement": "회한의 검",
  "Confiteor": "고백 기도",
  "Blade of Faith": "신의의 검",
  "Blade of Truth": "진실의 검",
  "Blade of Valor": "용맹의 검",
  "Holy Spirit": "성령의 권능",
  "Holy Circle": "신성한 원",
  "Goring Blade": "꿰뚫는 검격",
  "Expiacion": "속죄",
  "Circle of Scorn": "파멸의 진",
  "Intervene": "개입",
  "Shield Lob": "방패 던지기",
  "Rampart": "철벽 방어",
  "Sentinel": "경계",
  "Hallowed Ground": "천하무적",
  "Bulwark": "방패 각성",
  "Sheltron": "방벽",
  "Holy Sheltron": "신성한 방벽",
  "Cover": "감싸기",
  "Passage of Arms": "결연한 수호자",
  "Divine Veil": "신성한 보호막",
  "Intervention": "중재",
  "Requiescat": "안식 기도",
  "Fight or Flight": "임전무퇴",
  "Provoke": "도발",
  "Shirk": "기피",
  "Reprisal": "앙갚음",
  "Low Blow": "비열한 기습",
  "Interject": "말참견",
  "Arm's Length": "거리 유지",
  "Sprint": "전력 질주"
}